[
    {"id":1,"name":"朱啸营","password":"f02f750e65ebba95ab9493cd","sex":0,"email":"1144709265@qq.com","phone":"13041086186","departmentId":"1","jobId":"1","desc":"珠峰培训最高管理员账户","time":1568640222269,"state":0},
    {"id":2,"name":"周啸天","password":"8376ac810bb9f231d28fcf1f","sex":0,"email":"zhouxiaotian@qq.com","phone":"18310612838","departmentId":1,"jobId":"1","desc":"ssssaaaaaa","time":1568640222269,"state":0},
    {"id":3,"name":"程亚光","password":"8376ac810bb9f231d28fcf1f","sex":"0","email":"chengyanguang@126.com","phone":"15356985478","departmentId":"3","jobId":"3","desc":"我是程亚光，来自于星星的你","time":1568955194924,"state":0},

    {"id":4,"name":"杨云","password":"f02f750e65ebba95ab9493cd","sex":"0","email":"dfdf@kk.com","phone":"13592036038","departmentId":"2","jobId":"2","desc":"提高思想认识","time":1599628200930,"state":0,"userId":"null"},      
                   
    {"id":5,"name":"金云","password":"8376ac810bb9f231d28fcf1f","sex":"0","email":"dfdf@kk.com","phone":"13592036037","departmentId":"2","jobId":"3","desc":"提高思想认识","time":1599628200930,"state":0,"userId":"null"},

    {"id":6,"name":"王金光","password":"8376ac810bb9f231d28fcf1f","sex":"1","email":"sds@jjds.com","phone":"13592036036","departmentId":"3","jobId":"4","desc":"职建设院校，国家国防教育特色学校，国家首批现代学徒制试点学校，河南省","time":1599652347355,"state":0},
    
    {"id":7,"name":"我的了","password":"8376ac810bb9f231d28fcf1f","sex":"0","email":"trtrtr@gfgf.com","phone":"13592036035","departmentId":"4","jobId":"5","desc":"菁菁学子”与“莘莘学子”含义有什么不同?_作业帮","time":1599652431190,"state":0},
    
    {"id":8,"name":"我mmm的了","password":"8376ac810bb9f231d28fcf1f","sex":"1","email":"wwewc@lk.com","phone":"13888883231","departmentId":"3","jobId":"3","desc":"上不了本科不要急,为你推荐河南省内最好职业技术学.","time":1599652431190,"state":0},

    {"id":9,"name":"官方了","password":"8376ac810bb9f231d28fcf1f","sex":"1","email":"wwewc@lk.com","phone":"13888883233","departmentId":"3","jobId":"3","desc":"上不了本科不要急,为你推荐河南省内最好职业技术学","time":1599652431190,"state":0},

    {"id":10,"name":"全球","password":"8376ac810bb9f231d28fcf1f","sex":"0","email":"wsqws@sd.com","phone":"13592036031","departmentId":"3","jobId":"3","desc":"控制好思想","time":1599979095323,"state":0},
    
    {"id":11,"name":"1球","password":"8376ac810bb9f231d28fcf1f","sex":"0","email":"wsqws@sd.com","phone":"13592036032","departmentId":"3","jobId":"3","desc":"控制好思想","time":1599979095323,"state":0},{"id":12,"name":"2球","password":"8376ac810bb9f231d28fcf1f","sex":"0","email":"wsqws@sd.com","phone":"13592036033","departmentId":"3","jobId":"3","desc":"控制好思想","time":1599979095323,"state":0},{"id":13,"name":"3球","password":"8376ac810bb9f231d28fcf1f","sex":"0","email":"wsqws@sd.com","phone":"13592036034","departmentId":"3","jobId":"3","desc":"控制好思想","time":1599979095323,"state":0},{"id":14,"name":"1冠福","password":"8376ac810bb9f231d28fcf1f","sex":"0","email":"冠福股份","phone":"13592036045","departmentId":"5","jobId":"5","desc":"计划计划计划22","time":1610353671086,"state":0},{"id":15,"name":"秦可凉","password":"8376ac810bb9f231d28fcf1f","sex":"0","email":"冠福股份","phone":"13592036043","departmentId":"5","jobId":"5","desc":"计划计划计划22","time":1610353671086,"state":0},{"id":16,"name":"秦春阳","password":"8376ac810bb9f231d28fcf1f","sex":"0","email":"冠福股份","phone":"13592076021","departmentId":"5","jobId":"5","desc":"rerreer计划22","time":1610353671086,"state":0}]