[{"id":1,"customerId":"27","visitText":"刚发的","visitTime":"2021/01/04/22:38:11","time":1568974134992,"state":0},{"id":11,"customerId":"57","visitText":"njjhhfsd343sessd","visitTime":"2021/01/04/01:49:45","time":1609696191955,"state":0},{"id":12,"customerId":"57","visitText":"yyyyyyyyy","visitTime":"2021/01/04/01:50:38","time":1609696242632,"state":0},{"id":13,"customerId":"57","visitText":"万千瓦多多无","visitTime":"2021/01/04/02:36:41","time":1609699007823,"state":0},{"id":14,"customerId":"27","visitText":"都让人若若若若若若若若若","visitTime":"2021/01/05/00:00:44","time":1609776048823,"state":0},{"id":15,"customerId":"27","visitText":"都让人若结婚若若若若若若若若","visitTime":"2021/01/05/00:00:44","time":1609778476734,"state":0}]